zopyx_ssl_cert_check/__init__.py
zopyx_ssl_cert_check/main.py
zopyx_ssl_cert_check-0.4.3.dist-info/WHEEL
zopyx_ssl_cert_check-0.4.3.dist-info/entry_points.txt
zopyx_ssl_cert_check-0.4.3.dist-info/METADATA
zopyx_ssl_cert_check-0.4.3.dist-info/RECORD
