Metadata-Version: 2.4
Name: zopyx-ssl-cert-check
Version: 0.4.3
Summary: A tool to check SSL certificate expiration dates.
Author: Andreas Jung
Author-email: Andreas Jung <info@zopyx.com>
License-Expression: MIT
Requires-Dist: rich
Requires-Python: >=3.12
